README.markdown
multisched.py
setup.py
multisched.egg-info/PKG-INFO
multisched.egg-info/SOURCES.txt
multisched.egg-info/dependency_links.txt
multisched.egg-info/top_level.txt