Metadata-Version: 1.1
Name: multisched
Version: 0.1.4
Summary: UNKNOWN
Home-page: http://pypi.python.org/pypi/multisched/
Author: Adam Tauber <asciimoo>
Author-email: asciimoo@faszkorbacs.hu
License: AGPLv3+
Keywords: threaded scheduler
Platform: UNKNOWN
Classifier: Development Status :: 4 - Beta
Classifier: License :: OSI Approved :: GNU Affero General Public License v3
